Metadata-Version: 2.1
Name: dcdm
Version: 1.2.0a0
Summary: cdm is a commend line Download Manger
Home-page: https://github.com/DoostanKhas/cdm 
Author: doostanKhas
Author-email: doostanKhas@gmail.com
License: Apache 2.0
Platform: UNKNOWN
Classifier: License :: OSI Approved :: Apache Software License
Classifier: Programming Language :: Python :: 3.6
Classifier: Programming Language :: Python :: 3.7
Classifier: Programming Language :: Python :: 3.8
Classifier: Programming Language :: Python :: 3.9
Provides-Extra: dev
License-File: LICENSE
